pydantree-0.1.1.dist-info/METADATA
pydantree-0.1.1.dist-info/WHEEL
pydantree-0.1.1.dist-info/entry_points.txt
pydantree/__init__.py
pydantree/data/grammar-schema.json
pydantree/data/languages/python/grammar.json
pydantree/data/languages/python/node-types.json
pydantree/data/languages/rust/grammar.json
pydantree/data/languages/rust/node-types.json
pydantree/grammar/README.md
pydantree/grammar/__init__.py
pydantree/grammar/amend_dcg_models.py
pydantree/grammar/models.py
pydantree/grammar/view.py
pydantree/interface/__init__.py
pydantree/interface/cli.py
pydantree/interface/models.py
pydantree/nodes/__init__.py
pydantree/nodes/models.py
pydantree/nodes/view.py
pydantree/paths.py
pydantree-0.1.1.dist-info/RECORD
